{
    "id": "skill-nokigu",
    "name": "農機具章",
    "cert": "true",
    "url": "https://www.scout.or.jp/member/skill-nokigu",
    "details": [
        {
            "id": "1",
            "number": "1",
            "description": "現在一般的に使用している農機具類の名称、使用法、手入れ法を説明できること。"
        },
        {
            "id": "2",
            "number": "2",
            "description": "原動機付農業機械と同じ作業を人力または蓄力で行う場合と能率の差、機械化による功罪を説明できること。"
        },
        {
            "id": "3",
            "number": "3",
            "description": "次の機器のうち3種以上の運転操作ができ、安全と保守管理の注意点を説明できること。\nア) コンバイン\nイ) 草刈機\nウ) 耕うん機\nエ) 通風乾燥器\nオ) 自動田植機\nカ) 病虫害防除機\nキ) 揚排水ポンプ\nク) 脱穀機"
        },
        {
            "id": "4",
            "number": "4",
            "description": "農機具の移り変りについて、レポートを提出すること。"
        },
        {
            "id": "5",
            "number": "5",
            "description": "農機具の新案、改良の図面等を提出し、説明できること。"
        }
    ]
}