{
    "id": "skill-dojyo",
    "name": "土壌章",
    "cert": "true",
    "url": "https://www.scout.or.jp/member/skill-dojyo",
    "detail": [
        {
            "id": "1",
            "number": "1",
            "description": "酸性土壌の検出法2種以上について説明でき、その1種について実演すること。"
        },
        {
            "id": "2",
            "number": "2",
            "description": "土壌の化学的成分を説明できること。"
        },
        {
            "id": "3",
            "number": "3",
            "description": "湿土の取り扱いと改良法について説明できること。"
        },
        {
            "id": "4",
            "number": "4",
            "description": "農耕地の土壌改良法3種以上をあげ、説明できること。"
        },
        {
            "id": "5",
            "number": "5",
            "description": "次のうち1種について説明できること。\nア) 農耕地または芝生の地力の劣化防止法2種以上\nイ) 荒地の再生法3種以上"
        },
        {
            "id": "6",
            "number": "6",
            "description": "農耕地で5種の耕土を採取し、びん詰めとして標本を作り、採取の場所を記して提出すること。"
        },
        {
            "id": "7",
            "number": "7",
            "description": "近隣の地形をもとに土壌の崩壊を防ぐプランを立案し、設計図により説明できること。"
        }
    ]
}