{
    "id": "skill-tuyaku",
    "name": "通訳章",
    "cert": "true",
    "url": "https://www.scout.or.jp/member/skill-tuyaku",
    "details": [
        {
            "id": "1",
            "number": "1",
            "description": "公益財団法人 日本英語検定協会の実施する実用英語技能検定3級以上に合格するか、またはそれと同等の実力を有すること。"
        },
        {
            "id": "2",
            "number": "2",
            "description": "英語による通訳、説明などを求められる次の場合を想定し、「自分の英語で」作文し、口頭で発表すること。\nア) 道案内\nイ) 買物\nウ) 簡単な紹介・伝言\nエ) 掲示文の大体の説明\nオ) 祭り、行事、品物などの説明"
        },
        {
            "id": "3",
            "number": "3",
            "description": "ラジオの英語放送を継続して聞き、ニュース・解説・天気予報・スポット・アナウンスメント・ドラマなどのうち、3つ以上の内容を理解し得た範囲で、日本語でかいつまんで報告する（翻訳ではない）。報告書には聞いた日時、番組名を記入すること。"
        },
        {
            "id": "4",
            "number": "4",
            "description": "簡単な日記を継続して英語で書き、さしつかえない部分を考査時に提示すること。"
        }
    ]
}