{
    "id": "skill-syashin",
    "name": "写真章",
    "cert": "true",
    "url": "https://www.scout.or.jp/member/skill-syashin",
    "details": [
        {
            "sort": 1,
            "number": "1",
            "description": "自分の使っている写真機に応じて次の項目について説明をすること。\nア　フィルムカメラの場合\n(ｱ)　フィルム感度と露出、シャッター速度の関係について\n(ｲ)　ネガフィルムとポジフィルムについて\nイ　デジタルカメラの場合\n(ｱ)　画素数の単位について\n(ｲ)　記憶媒体の種類と特徴について"
        },
        {
            "sort": 2,
            "number": "2",
            "description": "露出計の種類を３つ以上挙げ、そのうちの２種類について、その原理と取り扱い上の注意事項を説明すること。"
        },
        {
            "sort": 3,
            "number": "3",
            "description": "示された作品5種について、撮影、印画、処理、構図、照明、採光、その他の観点より、批評し優劣の順位をつけること。"
        },
        {
            "sort": 4,
            "number": "4",
            "description": "3か月以上の団、隊の活動の写真記録を作成し、団内に発表すること。"
        },
        {
            "sort": 5,
            "number": "5",
            "description": "作品を2回以上展示会に出品、または投稿した経験を有すること。"
        }
    ]
}