{
    "id": "falcon",
    "name": "隼スカウト章",
    "detailIndex": [
        "基本",
        "スカウト技能",
        "スカウト精神",
        "奉仕",
        "信仰奨励",
        "成長と貢献"
    ],
    "detail": [
        {
            "id": "0",
            "number": "1-1",
            "description": "ベンチャー章取得後、最低4か月間「ちかい」と「おきて」の実践に最善をつくし、隊集会で発表する。",
            "cert": "true"
        },
        {
            "id": "1",
            "number": "2-1",
            "description": "自ら課題を設定し、安全、衛生、環境に配慮した、2泊3日以上の移動キャンプを計画、実施、評価をまとめ報告する。",
            "cert": "true"
        },
        {
            "id": "2",
            "number": "2-2",
            "description": "技能章から「野営章」、「野外炊事章」を取得する。",
            "cert": "true"
        },
        {
            "id": "3",
            "number": "2-3",
            "description": "考査員認定の技能章から「救急章」を含む３個取得する（BS時に取得した考査員認定の技能章を含む）。",
            "cert": "true"
        },
        {
            "id": "4",
            "number": "3-1",
            "description": "地区や県の仲間や地域の仲間と、自分たちの活動や社会における課題をフォーラム形式で話し合い、将来につながる活動を実施する。",
            "cert": "true"
        },
        {
            "id": "5",
            "number": "4-1",
            "description": "隊や団、地域社会に貢献することを課題として企画、計画し、実績を隊長に提出する。",
            "cert": "true"
        },
        {
            "id": "6",
            "number": "5-1",
            "description": "自分が信仰する宗教もしくは自分の心に触れた教宗派の歴史と教えを知る。",
            "cert": "true"
        },
        {
            "id": "7",
            "number": "6-1",
            "description": "個人プロジェクトまたは、チームの主要な役割として、プロジェクトを計画、実施し、隊長に報告書を提出し、「隼プロジェクト」として団行事等で発表する。",
            "cert": "true"
        }
    ]
}